MANIFEST.in
README
cubicweb-trustedauth.spec
requirements-test.txt
setup.py
tox.ini
cubicweb_trustedauth/__init__.py
cubicweb_trustedauth/__pkginfo__.py
cubicweb_trustedauth/authplugin.py
cubicweb_trustedauth/hooks.py
cubicweb_trustedauth/pconfig.py
cubicweb_trustedauth/schema.py
cubicweb_trustedauth/views.py
cubicweb_trustedauth.egg-info/PKG-INFO
cubicweb_trustedauth.egg-info/SOURCES.txt
cubicweb_trustedauth.egg-info/dependency_links.txt
cubicweb_trustedauth.egg-info/entry_points.txt
cubicweb_trustedauth.egg-info/not-zip-safe
cubicweb_trustedauth.egg-info/requires.txt
cubicweb_trustedauth.egg-info/top_level.txt
cubicweb_trustedauth/i18n/en.po
cubicweb_trustedauth/i18n/es.po
cubicweb_trustedauth/i18n/fr.po
cubicweb_trustedauth/migration/0.6.0_Any.py
cubicweb_trustedauth/migration/postcreate.py
cubicweb_trustedauth/wdoc/setup.rst
cubicweb_trustedauth/wdoc/setup_fr
debian/changelog
debian/compat
debian/control
debian/copyright
debian/rules
test/test_pyramid.py
test/unittest_trustedauth.py
test/data/bootstrap_cubes