Metadata-Version: 1.1
Name: cubicweb-trustedauth
Version: 0.6.0
Summary: authentication plugin for cubicweb instances behind a trusted reverse proxy managing authentication  (eg. apache + kerberos)
Home-page: http://www.cubicweb.org/project/cubicweb-trustedauth
Author: LOGILAB S.A. (Paris, FRANCE)
Author-email: contact@logilab.fr
License: LGPL
Platform: UNKNOWN
Classifier: Environment :: Web Environment
Classifier: Framework :: CubicWeb
Classifier: Programming Language :: Python
